ether/__init__.py
ether/cell.py
ether/core.py
ether/topology.py
ether/util.py
ether/vis.py
ether/vivaldi.py
ether/blocks/__init__.py
ether/blocks/cells.py
ether/blocks/hosts.py
ether/blocks/nodes.py
ether/cli/__init__.py
ether/cli/inet.py
ether/converter/__init__.py
ether/converter/pyvis.py
ether/inet/__init__.py
ether/inet/graph.py
ether/inet/fetch/__init__.py
ether/inet/fetch/cloudping.py
ether/inet/fetch/data.py
ether/inet/fetch/gcloudping.py
ether/inet/fetch/wondernetwork.py
ether/inet/graphs/cloudping_2020_05_18.graphml
ether/inet/graphs/cloudping_2020_06_20.graphml
ether/inet/graphs/cloudping_latest.graphml
ether/inet/graphs/gcloudping_2020_05_18.graphml
ether/inet/graphs/gcloudping_latest.graphml
ether/inet/graphs/wondernetwork_2020_05_18.graphml
ether/inet/graphs/wondernetwork_2020_06_20.graphml
ether/inet/graphs/wondernetwork_latest.graphml
ether/qos/__init__.py
ether/qos/latency.py
ether/scenarios/__init__.py
ether/scenarios/cloudregions.py
ether/scenarios/industrialiot.py
ether/scenarios/urbansensing.py
examples/__init__.py
examples/iiot.py
examples/urbansensing.py
examples/vivaldi/__init__.py
examples/vivaldi/client_experiment.py
examples/vivaldi/cloud_regions.py
examples/vivaldi/urban_sensing.py
examples/vivaldi/util.py
tests/__init__.py
tests/test_networkx.py
tests/test_nodes.py
tests/inet/__init__.py
tests/inet/test_graph.py
tests/inet/fetch/__init__.py
tests/inet/fetch/test_cloudping.py
tests/inet/fetch/test_gcloudping.py
tests/inet/fetch/test_wondernetwork.py
edgerun_ether-0.3.3.dist-info/METADATA
edgerun_ether-0.3.3.dist-info/WHEEL
edgerun_ether-0.3.3.dist-info/top_level.txt
edgerun_ether-0.3.3.dist-info/RECORD
