Metadata-Version: 2.1
Name: edgerun-ether
Version: 0.3.3
Summary: Ether - Synthesize plausible edge infrastructure topologies
Home-page: https://github.com/edgerun/ether
Author: Thomas Rausch
Author-email: t.rausch@dsg.tuwien.ac.at
License: UNKNOWN
Platform: UNKNOWN
Classifier: Programming Language :: Python :: 3
Classifier: Operating System :: OS Independent
Requires-Dist: matplotlib (==3.4.2)
Requires-Dist: networkx (==2.4)
Requires-Dist: numpy (==1.21.0)
Requires-Dist: pandas (==1.2.5)
Requires-Dist: scipy (==1.7.0)
Requires-Dist: simpy (==3.0.11)
Requires-Dist: srds (==0.1.0)
Requires-Dist: requests (==2.23.0)
Requires-Dist: scikit-learn (~=0.24.2)
Requires-Dist: setuptools (~=50.3.0)
Requires-Dist: pyvis (~=0.1.8.2)
